weathercop-0.2.0.dist-info/WHEEL
weathercop-0.2.0.dist-info/top_level.txt
weathercop-0.2.0.dist-info/METADATA
weathercop-0.2.0.dist-info/RECORD
weathercop-0.2.0.dist-info/licenses/LICENSE
weathercop/multisite_conditional.py
weathercop/vine.py
weathercop/multisite.py
weathercop/cop_conf.py
weathercop/plotting.py
weathercop/stats.py
weathercop/cvine.c
weathercop/multisite_annual.py
weathercop/cinv_cdf.cpython-313-x86_64-linux-gnu.so
weathercop/seasonal_cop.py
weathercop/cvine.pyx
weathercop/copulae.py
weathercop/normal_conditional.pyx
weathercop/ensemble_plotting.py
weathercop/cvine.cpython-313-x86_64-linux-gnu.so
weathercop/cinv_cdf.pyx
weathercop/find_copula.py
weathercop/opendata_vg_conf.py
weathercop/external.py
weathercop/__init__.py
weathercop/cinv_cdf.c
weathercop/tools.py
weathercop/ufuncs/setup.py
weathercop/ufuncs/sympy_cache.json
weathercop/ufuncs/__init__.py
weathercop/tests/test_multisite.py
weathercop/tests/memory_diagnostics.py
weathercop/tests/prof_seasonal_cvine.py
weathercop/tests/assertion_utils.py
weathercop/tests/xarray_tracking.py
weathercop/tests/generate_test_data.py
weathercop/tests/test_memory_optimization.py
weathercop/tests/test_assertion_utils.py
weathercop/tests/test_config_debug.py
weathercop/tests/test_cyvine.py
weathercop/tests/test_seasonal_cop.py
weathercop/tests/test_config.py
weathercop/tests/test_copulae.py
weathercop/tests/test_multisite_conditional.py
weathercop/tests/test_memory_profile.py
weathercop/tests/test_ensemble.py
weathercop/tests/how_do_xarray_dims_work.py
weathercop/tests/test_vine.py
weathercop/tests/conftest.py
weathercop/configs/__init__.py
weathercop/configs/dwd_vg_conf.py
