Metadata-Version: 2.4
Name: weathercop
Version: 0.2.0
Summary: A Copula-based Weather Generator
Author-email: iskur <32363199+iskur@users.noreply.github.com>
License-Expression: MIT
Requires-Python: >=3.13
License-File: LICENSE
Requires-Dist: cartopy>=0.24.1
Requires-Dist: dask>=2025.11.0
Requires-Dist: dill>=0.4.0
Requires-Dist: matplotlib>=3.10.3
Requires-Dist: netcdf4>=1.7.2
Requires-Dist: networkx>=3.5
Requires-Dist: numexpr>=2.11.0
Requires-Dist: numpy>=2.3.1
Requires-Dist: pandas>=2.3.0
Requires-Dist: scipy>=1.16.0
Requires-Dist: sympy>=1.14.0
Requires-Dist: timezonefinder>=6.5.9
Requires-Dist: tqdm>=4.67.1
Requires-Dist: varwg>=1.4.2
Requires-Dist: xarray>=2025.6.1
Dynamic: license-file
